Metadata-Version: 1.0
Name: gnb-distributions
Version: 0.1
Summary: Gaussian and Bionomial distributions
Home-page: UNKNOWN
Author: Daniel Chris Daniil
Author-email: dannyd1997@g.ucla.edu
License: UNKNOWN
Platform: UNKNOWN
